{
  "config_path": "/Users/ajithsenthil/Desktop/CompPsychoVid/HERMES/data/network_message_passing/surveillance_mesh.json",
  "params": {
    "bp_delay_weight": 0.25,
    "lp_alpha_delay": 1.0,
    "lp_alpha_distance": 1.2,
    "lp_alpha_downstream_queue": 0.08,
    "lp_send_reward": 1200.0
  },
  "results": {
    "backpressure": {
      "coordination_kpis": {
        "alert_duplicate_rate": 0.9059500959692899,
        "handoff_success_rate": 0.8398203592814372,
        "handoff_timely_success_rate": 0.7529940119760479
      },
      "per_commodity": {
        "alert_cam1": {
          "avg_latency": 2.842741935483871,
          "avg_unique_latency": 2.7576923076923077,
          "copies": 2,
          "delivered": 496,
          "delivered_unique": 260,
          "delivery_ratio": 0.9465648854961832,
          "dropped": 23,
          "duplicate_deliveries": 236,
          "duplicate_per_unique": 0.9076923076923077,
          "injected": 524,
          "injected_unique": 262,
          "kind": "alert",
          "p95_latency": 5.0,
          "p95_unique_latency": 5.0,
          "stale_packet_deliveries": 68,
          "stale_unique_deliveries": 32,
          "stale_unique_ratio": 0.12307692307692308,
          "timely_unique_deliveries": 228,
          "timely_unique_ratio": 0.8702290076335878,
          "ttl_steps": 3,
          "unique_delivery_ratio": 0.9923664122137404
        },
        "alert_cam2": {
          "avg_latency": 2.681933842239186,
          "avg_unique_latency": 2.622549019607843,
          "copies": 2,
          "delivered": 393,
          "delivered_unique": 204,
          "delivery_ratio": 0.7119565217391305,
          "dropped": 15,
          "duplicate_deliveries": 189,
          "duplicate_per_unique": 0.9264705882352942,
          "injected": 552,
          "injected_unique": 276,
          "kind": "alert",
          "p95_latency": 5.0,
          "p95_unique_latency": 5.0,
          "stale_packet_deliveries": 57,
          "stale_unique_deliveries": 26,
          "stale_unique_ratio": 0.12745098039215685,
          "timely_unique_deliveries": 178,
          "timely_unique_ratio": 0.644927536231884,
          "ttl_steps": 3,
          "unique_delivery_ratio": 0.7391304347826086
        },
        "alert_cam3": {
          "avg_latency": 2.795620437956204,
          "avg_unique_latency": 2.7395833333333335,
          "copies": 2,
          "delivered": 548,
          "delivered_unique": 288,
          "delivery_ratio": 0.9383561643835616,
          "dropped": 29,
          "duplicate_deliveries": 260,
          "duplicate_per_unique": 0.9027777777777778,
          "injected": 584,
          "injected_unique": 292,
          "kind": "alert",
          "p95_latency": 5.0,
          "p95_unique_latency": 4.0,
          "stale_packet_deliveries": 61,
          "stale_unique_deliveries": 29,
          "stale_unique_ratio": 0.10069444444444445,
          "timely_unique_deliveries": 259,
          "timely_unique_ratio": 0.886986301369863,
          "ttl_steps": 3,
          "unique_delivery_ratio": 0.9863013698630136
        },
        "alert_cam4": {
          "avg_latency": 2.75591985428051,
          "avg_unique_latency": 2.7275862068965515,
          "copies": 2,
          "delivered": 549,
          "delivered_unique": 290,
          "delivery_ratio": 0.9336734693877551,
          "dropped": 33,
          "duplicate_deliveries": 259,
          "duplicate_per_unique": 0.8931034482758621,
          "injected": 588,
          "injected_unique": 294,
          "kind": "alert",
          "p95_latency": 5.0,
          "p95_unique_latency": 5.0,
          "stale_packet_deliveries": 65,
          "stale_unique_deliveries": 31,
          "stale_unique_ratio": 0.10689655172413794,
          "timely_unique_deliveries": 259,
          "timely_unique_ratio": 0.8809523809523809,
          "ttl_steps": 3,
          "unique_delivery_ratio": 0.9863945578231292
        },
        "handoff_1_2": {
          "avg_latency": 1.8706467661691542,
          "avg_unique_latency": 1.8706467661691542,
          "copies": 1,
          "delivered": 201,
          "delivered_unique": 201,
          "delivery_ratio": 0.9710144927536232,
          "dropped": 6,
          "duplicate_deliveries": 0,
          "duplicate_per_unique": 0.0,
          "injected": 207,
          "injected_unique": 207,
          "kind": "handoff",
          "p95_latency": 5.0,
          "p95_unique_latency": 5.0,
          "stale_packet_deliveries": 13,
          "stale_unique_deliveries": 13,
          "stale_unique_ratio": 0.06467661691542288,
          "timely_unique_deliveries": 188,
          "timely_unique_ratio": 0.9082125603864735,
          "ttl_steps": 4,
          "unique_delivery_ratio": 0.9710144927536232
        },
        "handoff_2_3": {
          "avg_latency": 3.018633540372671,
          "avg_unique_latency": 3.018633540372671,
          "copies": 1,
          "delivered": 161,
          "delivered_unique": 161,
          "delivery_ratio": 0.7,
          "dropped": 10,
          "duplicate_deliveries": 0,
          "duplicate_per_unique": 0.0,
          "injected": 230,
          "injected_unique": 230,
          "kind": "handoff",
          "p95_latency": 13.0,
          "p95_unique_latency": 13.0,
          "stale_packet_deliveries": 29,
          "stale_unique_deliveries": 29,
          "stale_unique_ratio": 0.18012422360248448,
          "timely_unique_deliveries": 132,
          "timely_unique_ratio": 0.5739130434782609,
          "ttl_steps": 4,
          "unique_delivery_ratio": 0.7
        },
        "handoff_3_4": {
          "avg_latency": 2.693467336683417,
          "avg_unique_latency": 2.693467336683417,
          "copies": 1,
          "delivered": 199,
          "delivered_unique": 199,
          "delivery_ratio": 0.8614718614718615,
          "dropped": 28,
          "duplicate_deliveries": 0,
          "duplicate_per_unique": 0.0,
          "injected": 231,
          "injected_unique": 231,
          "kind": "handoff",
          "p95_latency": 6.0,
          "p95_unique_latency": 6.0,
          "stale_packet_deliveries": 16,
          "stale_unique_deliveries": 16,
          "stale_unique_ratio": 0.08040201005025126,
          "timely_unique_deliveries": 183,
          "timely_unique_ratio": 0.7922077922077922,
          "ttl_steps": 4,
          "unique_delivery_ratio": 0.8614718614718615
        },
        "heartbeat_1": {
          "avg_latency": 3.686046511627907,
          "avg_unique_latency": 3.686046511627907,
          "copies": 1,
          "delivered": 172,
          "delivered_unique": 172,
          "delivery_ratio": 0.9398907103825137,
          "dropped": 8,
          "duplicate_deliveries": 0,
          "duplicate_per_unique": 0.0,
          "injected": 183,
          "injected_unique": 183,
          "kind": "heartbeat",
          "p95_latency": 10.349999999999966,
          "p95_unique_latency": 10.349999999999966,
          "stale_packet_deliveries": 77,
          "stale_unique_deliveries": 77,
          "stale_unique_ratio": 0.4476744186046512,
          "timely_unique_deliveries": 95,
          "timely_unique_ratio": 0.5191256830601093,
          "ttl_steps": 2,
          "unique_delivery_ratio": 0.9398907103825137
        },
        "heartbeat_2": {
          "avg_latency": 4.357142857142857,
          "avg_unique_latency": 4.357142857142857,
          "copies": 1,
          "delivered": 168,
          "delivered_unique": 168,
          "delivery_ratio": 0.7813953488372093,
          "dropped": 8,
          "duplicate_deliveries": 0,
          "duplicate_per_unique": 0.0,
          "injected": 215,
          "injected_unique": 215,
          "kind": "heartbeat",
          "p95_latency": 11.300000000000011,
          "p95_unique_latency": 11.300000000000011,
          "stale_packet_deliveries": 95,
          "stale_unique_deliveries": 95,
          "stale_unique_ratio": 0.5654761904761905,
          "timely_unique_deliveries": 73,
          "timely_unique_ratio": 0.3395348837209302,
          "ttl_steps": 2,
          "unique_delivery_ratio": 0.7813953488372093
        },
        "heartbeat_3": {
          "avg_latency": 3.6153846153846154,
          "avg_unique_latency": 3.6153846153846154,
          "copies": 1,
          "delivered": 156,
          "delivered_unique": 156,
          "delivery_ratio": 0.9017341040462428,
          "dropped": 11,
          "duplicate_deliveries": 0,
          "duplicate_per_unique": 0.0,
          "injected": 173,
          "injected_unique": 173,
          "kind": "heartbeat",
          "p95_latency": 11.0,
          "p95_unique_latency": 11.0,
          "stale_packet_deliveries": 71,
          "stale_unique_deliveries": 71,
          "stale_unique_ratio": 0.4551282051282051,
          "timely_unique_deliveries": 85,
          "timely_unique_ratio": 0.4913294797687861,
          "ttl_steps": 2,
          "unique_delivery_ratio": 0.9017341040462428
        },
        "heartbeat_4": {
          "avg_latency": 3.9441340782122905,
          "avg_unique_latency": 3.9441340782122905,
          "copies": 1,
          "delivered": 179,
          "delivered_unique": 179,
          "delivery_ratio": 0.9040404040404041,
          "dropped": 14,
          "duplicate_deliveries": 0,
          "duplicate_per_unique": 0.0,
          "injected": 198,
          "injected_unique": 198,
          "kind": "heartbeat",
          "p95_latency": 13.0,
          "p95_unique_latency": 13.0,
          "stale_packet_deliveries": 87,
          "stale_unique_deliveries": 87,
          "stale_unique_ratio": 0.4860335195530726,
          "timely_unique_deliveries": 92,
          "timely_unique_ratio": 0.46464646464646464,
          "ttl_steps": 2,
          "unique_delivery_ratio": 0.9040404040404041
        },
        "track_cam1": {
          "avg_latency": 2.538374717832957,
          "avg_unique_latency": 2.538374717832957,
          "copies": 1,
          "delivered": 886,
          "delivered_unique": 886,
          "delivery_ratio": 0.9526881720430107,
          "dropped": 37,
          "duplicate_deliveries": 0,
          "duplicate_per_unique": 0.0,
          "injected": 930,
          "injected_unique": 930,
          "kind": "track",
          "p95_latency": 4.0,
          "p95_unique_latency": 4.0,
          "stale_packet_deliveries": 1,
          "stale_unique_deliveries": 1,
          "stale_unique_ratio": 0.001128668171557562,
          "timely_unique_deliveries": 885,
          "timely_unique_ratio": 0.9516129032258065,
          "ttl_steps": 8,
          "unique_delivery_ratio": 0.9526881720430107
        },
        "track_cam2": {
          "avg_latency": 2.6777777777777776,
          "avg_unique_latency": 2.6777777777777776,
          "copies": 1,
          "delivered": 720,
          "delivered_unique": 720,
          "delivery_ratio": 0.7563025210084033,
          "dropped": 30,
          "duplicate_deliveries": 0,
          "duplicate_per_unique": 0.0,
          "injected": 952,
          "injected_unique": 952,
          "kind": "track",
          "p95_latency": 5.0,
          "p95_unique_latency": 5.0,
          "stale_packet_deliveries": 4,
          "stale_unique_deliveries": 4,
          "stale_unique_ratio": 0.005555555555555556,
          "timely_unique_deliveries": 716,
          "timely_unique_ratio": 0.7521008403361344,
          "ttl_steps": 8,
          "unique_delivery_ratio": 0.7563025210084033
        },
        "track_cam3": {
          "avg_latency": 2.797604790419162,
          "avg_unique_latency": 2.797604790419162,
          "copies": 1,
          "delivered": 835,
          "delivered_unique": 835,
          "delivery_ratio": 0.9329608938547486,
          "dropped": 44,
          "duplicate_deliveries": 0,
          "duplicate_per_unique": 0.0,
          "injected": 895,
          "injected_unique": 895,
          "kind": "track",
          "p95_latency": 5.0,
          "p95_unique_latency": 5.0,
          "stale_packet_deliveries": 6,
          "stale_unique_deliveries": 6,
          "stale_unique_ratio": 0.00718562874251497,
          "timely_unique_deliveries": 829,
          "timely_unique_ratio": 0.9262569832402234,
          "ttl_steps": 8,
          "unique_delivery_ratio": 0.9329608938547486
        },
        "track_cam4": {
          "avg_latency": 2.678733031674208,
          "avg_unique_latency": 2.678733031674208,
          "copies": 1,
          "delivered": 884,
          "delivered_unique": 884,
          "delivery_ratio": 0.9608695652173913,
          "dropped": 30,
          "duplicate_deliveries": 0,
          "duplicate_per_unique": 0.0,
          "injected": 920,
          "injected_unique": 920,
          "kind": "track",
          "p95_latency": 4.0,
          "p95_unique_latency": 4.0,
          "stale_packet_deliveries": 7,
          "stale_unique_deliveries": 7,
          "stale_unique_ratio": 0.007918552036199095,
          "timely_unique_deliveries": 877,
          "timely_unique_ratio": 0.9532608695652174,
          "ttl_steps": 8,
          "unique_delivery_ratio": 0.9608695652173913
        }
      },
      "policy": "backpressure",
      "steps": 320,
      "timeseries": {
        "backlog": [
          0,
          1,
          1,
          2,
          5,
          0,
          3,
          3,
          7,
          3,
          5,
          3,
          5,
          7,
          1,
          4,
          2,
          4,
          1,
          4,
          2,
          5,
          2,
          2,
          3,
          4,
          9,
          4,
          12,
          7,
          4,
          5,
          4,
          8,
          9,
          9,
          7,
          6,
          4,
          5,
          4,
          4,
          6,
          3,
          5,
          10,
          5,
          6,
          1,
          3,
          2,
          0,
          5,
          4,
          2,
          4,
          2,
          4,
          3,
          2,
          4,
          6,
          2,
          4,
          2,
          1,
          1,
          1,
          2,
          4,
          7,
          5,
          4,
          4,
          5,
          3,
          3,
          7,
          6,
          5,
          9,
          11,
          13,
          20,
          19,
          20,
          23,
          31,
          19,
          19,
          20,
          16,
          14,
          17,
          16,
          14,
          13,
          16,
          9,
          5,
          8,
          13,
          15,
          18,
          26,
          20,
          20,
          10,
          13,
          8,
          4,
          8,
          6,
          3,
          6,
          6,
          3,
          11,
          7,
          11,
          9,
          16,
          11,
          8,
          3,
          10,
          3,
          15,
          13,
          27,
          25,
          28,
          38,
          52,
          48,
          52,
          62,
          67,
          70,
          60,
          71,
          68,
          68,
          62,
          65,
          46,
          51,
          45,
          52,
          43,
          43,
          32,
          29,
          37,
          38,
          44,
          48,
          42,
          50,
          54,
          53,
          44,
          23,
          30,
          14,
          7,
          6,
          3,
          8,
          3,
          4,
          1,
          2,
          8,
          6,
          1,
          3,
          3,
          5,
          3,
          3,
          2,
          4,
          1,
          3,
          5,
          6,
          3,
          5,
          10,
          9,
          6,
          8,
          2,
          5,
          5,
          12,
          3,
          5,
          3,
          9,
          3,
          9,
          4,
          7,
          2,
          3,
          1,
          4,
          4,
          6,
          7,
          2,
          2,
          4,
          8,
          5,
          8,
          3,
          6,
          7,
          8,
          8,
          10,
          12,
          9,
          8,
          9,
          3,
          12,
          8,
          10,
          5,
          9,
          4,
          5,
          1,
          1,
          1,
          2,
          12,
          27,
          37,
          51,
          60,
          68,
          72,
          81,
          81,
          91,
          98,
          101,
          106,
          117,
          124,
          127,
          133,
          140,
          151,
          156,
          165,
          168,
          180,
          182,
          193,
          198,
          200,
          205,
          215,
          218,
          225,
          229,
          239,
          246,
          256,
          257,
          264,
          266,
          273,
          280,
          284,
          285,
          290,
          294,
          303,
          308,
          309,
          313,
          327,
          334,
          350,
          351,
          358,
          361,
          366,
          366,
          374,
          374,
          383,
          384,
          391,
          399,
          399,
          406,
          409,
          420,
          426,
          428,
          433,
          433,
          438,
          442,
          448,
          452,
          464,
          468,
          475,
          476,
          482,
          492,
          509
        ],
        "context": [
          "normal",
          "normal",
          "normal",
          "normal",
          "normal",
          "normal",
          "normal",
          "normal",
          "normal",
          "normal",
          "normal",
          "normal",
          "normal",
          "normal",
          "normal",
          "normal",
          "normal",
          "normal",
          "normal",
          "normal",
          "normal",
          "normal",
          "normal",
          "normal",
          "normal",
          "normal",
          "normal",
          "normal",
          "normal",
          "normal",
          "normal",
          "normal",
          "normal",
          "normal",
          "normal",
          "normal",
          "normal",
          "normal",
          "normal",
          "normal",
          "normal",
          "normal",
          "normal",
          "normal",
          "normal",
          "normal",
          "normal",
          "normal",
          "normal",
          "normal",
          "normal",
          "normal",
          "normal",
          "normal",
          "normal",
          "normal",
          "normal",
          "normal",
          "normal",
          "normal",
          "normal",
          "normal",
          "normal",
          "normal",
          "normal",
          "normal",
          "normal",
          "normal",
          "normal",
          "normal",
          "normal",
          "normal",
          "normal",
          "normal",
          "normal",
          "normal",
          "normal",
          "normal",
          "normal",
          "normal",
          "crowded",
          "crowded",
          "crowded",
          "crowded",
          "crowded",
          "crowded",
          "crowded",
          "crowded",
          "crowded",
          "crowded",
          "crowded",
          "crowded",
          "crowded",
          "crowded",
          "crowded",
          "crowded",
          "crowded",
          "crowded",
          "crowded",
          "crowded",
          "crowded",
          "crowded",
          "crowded",
          "crowded",
          "crowded",
          "crowded",
          "crowded",
          "crowded",
          "crowded",
          "crowded",
          "crowded",
          "crowded",
          "crowded",
          "crowded",
          "crowded",
          "crowded",
          "crowded",
          "crowded",
          "crowded",
          "crowded",
          "crowded",
          "crowded",
          "crowded",
          "crowded",
          "crowded",
          "crowded",
          "crowded",
          "crowded",
          "crowded",
          "crowded",
          "crowded",
          "crowded",
          "crowded",
          "crowded",
          "crowded",
          "crowded",
          "crowded",
          "crowded",
          "crowded",
          "crowded",
          "crowded",
          "crowded",
          "crowded",
          "crowded",
          "crowded",
          "crowded",
          "crowded",
          "crowded",
          "crowded",
          "crowded",
          "crowded",
          "crowded",
          "crowded",
          "crowded",
          "crowded",
          "crowded",
          "crowded",
          "crowded",
          "crowded",
          "crowded",
          "uplink_loss",
          "uplink_loss",
          "uplink_loss",
          "uplink_loss",
          "uplink_loss",
          "uplink_loss",
          "uplink_loss",
          "uplink_loss",
          "uplink_loss",
          "uplink_loss",
          "uplink_loss",
          "uplink_loss",
          "uplink_loss",
          "uplink_loss",
          "uplink_loss",
          "uplink_loss",
          "uplink_loss",
          "uplink_loss",
          "uplink_loss",
          "uplink_loss",
          "uplink_loss",
          "uplink_loss",
          "uplink_loss",
          "uplink_loss",
          "uplink_loss",
          "uplink_loss",
          "uplink_loss",
          "uplink_loss",
          "uplink_loss",
          "uplink_loss",
          "uplink_loss",
          "uplink_loss",
          "uplink_loss",
          "uplink_loss",
          "uplink_loss",
          "uplink_loss",
          "uplink_loss",
          "uplink_loss",
          "uplink_loss",
          "uplink_loss",
          "uplink_loss",
          "uplink_loss",
          "uplink_loss",
          "uplink_loss",
          "uplink_loss",
          "uplink_loss",
          "uplink_loss",
          "uplink_loss",
          "uplink_loss",
          "uplink_loss",
          "uplink_loss",
          "uplink_loss",
          "uplink_loss",
          "uplink_loss",
          "uplink_loss",
          "uplink_loss",
          "uplink_loss",
          "uplink_loss",
          "uplink_loss",
          "uplink_loss",
          "uplink_loss",
          "uplink_loss",
          "uplink_loss",
          "uplink_loss",
          "uplink_loss",
          "uplink_loss",
          "uplink_loss",
          "uplink_loss",
          "uplink_loss",
          "uplink_loss",
          "uplink_loss",
          "uplink_loss",
          "uplink_loss",
          "uplink_loss",
          "uplink_loss",
          "uplink_loss",
          "uplink_loss",
          "uplink_loss",
          "uplink_loss",
          "uplink_loss",
          "cam2_failure",
          "cam2_failure",
          "cam2_failure",
          "cam2_failure",
          "cam2_failure",
          "cam2_failure",
          "cam2_failure",
          "cam2_failure",
          "cam2_failure",
          "cam2_failure",
          "cam2_failure",
          "cam2_failure",
          "cam2_failure",
          "cam2_failure",
          "cam2_failure",
          "cam2_failure",
          "cam2_failure",
          "cam2_failure",
          "cam2_failure",
          "cam2_failure",
          "cam2_failure",
          "cam2_failure",
          "cam2_failure",
          "cam2_failure",
          "cam2_failure",
          "cam2_failure",
          "cam2_failure",
          "cam2_failure",
          "cam2_failure",
          "cam2_failure",
          "cam2_failure",
          "cam2_failure",
          "cam2_failure",
          "cam2_failure",
          "cam2_failure",
          "cam2_failure",
          "cam2_failure",
          "cam2_failure",
          "cam2_failure",
          "cam2_failure",
          "cam2_failure",
          "cam2_failure",
          "cam2_failure",
          "cam2_failure",
          "cam2_failure",
          "cam2_failure",
          "cam2_failure",
          "cam2_failure",
          "cam2_failure",
          "cam2_failure",
          "cam2_failure",
          "cam2_failure",
          "cam2_failure",
          "cam2_failure",
          "cam2_failure",
          "cam2_failure",
          "cam2_failure",
          "cam2_failure",
          "cam2_failure",
          "cam2_failure",
          "cam2_failure",
          "cam2_failure",
          "cam2_failure",
          "cam2_failure",
          "cam2_failure",
          "cam2_failure",
          "cam2_failure",
          "cam2_failure",
          "cam2_failure",
          "cam2_failure",
          "cam2_failure",
          "cam2_failure",
          "cam2_failure",
          "cam2_failure",
          "cam2_failure",
          "cam2_failure",
          "cam2_failure",
          "cam2_failure",
          "cam2_failure",
          "cam2_failure",
          "drain"
        ],
        "delivered": [
          0,
          1,
          22,
          13,
          27,
          23,
          21,
          24,
          22,
          16,
          25,
          17,
          19,
          18,
          22,
          10,
          23,
          14,
          26,
          15,
          24,
          11,
          18,
          21,
          20,
          24,
          19,
          26,
          23,
          31,
          21,
          18,
          19,
          21,
          23,
          12,
          27,
          20,
          27,
          16,
          25,
          24,
          11,
          24,
          15,
          22,
          23,
          17,
          23,
          32,
          23,
          22,
          19,
          21,
          21,
          20,
          28,
          18,
          19,
          25,
          15,
          22,
          22,
          29,
          17,
          25,
          15,
          18,
          19,
          16,
          9,
          26,
          20,
          27,
          26,
          16,
          14,
          15,
          16,
          20,
          26,
          18,
          28,
          18,
          26,
          26,
          27,
          29,
          31,
          27,
          28,
          28,
          26,
          28,
          31,
          26,
          32,
          27,
          20,
          31,
          28,
          27,
          31,
          28,
          27,
          28,
          26,
          36,
          32,
          26,
          24,
          28,
          29,
          30,
          24,
          25,
          19,
          26,
          20,
          26,
          26,
          18,
          27,
          27,
          26,
          26,
          27,
          28,
          25,
          29,
          26,
          27,
          25,
          28,
          29,
          25,
          27,
          29,
          27,
          27,
          30,
          29,
          31,
          27,
          25,
          26,
          28,
          27,
          26,
          27,
          28,
          28,
          24,
          27,
          28,
          27,
          26,
          30,
          26,
          31,
          28,
          28,
          26,
          25,
          29,
          25,
          27,
          26,
          17,
          26,
          17,
          22,
          16,
          23,
          17,
          20,
          12,
          20,
          19,
          13,
          22,
          17,
          22,
          24,
          12,
          26,
          15,
          23,
          10,
          16,
          19,
          23,
          25,
          22,
          23,
          18,
          18,
          19,
          17,
          23,
          15,
          21,
          20,
          22,
          19,
          19,
          18,
          14,
          14,
          10,
          19,
          16,
          26,
          18,
          19,
          16,
          24,
          16,
          17,
          15,
          23,
          25,
          14,
          21,
          20,
          20,
          25,
          26,
          28,
          15,
          25,
          10,
          28,
          13,
          22,
          19,
          29,
          28,
          23,
          20,
          20,
          23,
          12,
          22,
          10,
          22,
          15,
          15,
          23,
          12,
          28,
          13,
          17,
          13,
          12,
          14,
          20,
          13,
          12,
          8,
          9,
          17,
          11,
          13,
          7,
          20,
          5,
          22,
          18,
          17,
          9,
          18,
          18,
          8,
          14,
          16,
          10,
          20,
          15,
          14,
          14,
          14,
          16,
          15,
          9,
          19,
          13,
          14,
          18,
          10,
          14,
          22,
          13,
          19,
          5,
          18,
          5,
          16,
          12,
          17,
          12,
          17,
          16,
          12,
          10,
          11,
          20,
          7,
          22,
          15,
          13,
          11,
          7,
          17,
          6,
          11,
          15,
          16,
          17,
          14,
          17
        ],
        "dropped": [
          0,
          0,
          1,
          0,
          1,
          2,
          0,
          0,
          1,
          0,
          0,
          2,
          1,
          2,
          1,
          2,
          0,
          0,
          0,
          2,
          0,
          0,
          0,
          0,
          0,
          2,
          1,
          0,
          1,
          0,
          1,
          1,
          1,
          3,
          1,
          1,
          2,
          0,
          0,
          0,
          2,
          0,
          1,
          0,
          1,
          2,
          1,
          0,
          1,
          3,
          2,
          0,
          1,
          2,
          0,
          1,
          1,
          0,
          1,
          0,
          2,
          1,
          0,
          0,
          1,
          0,
          0,
          0,
          1,
          1,
          0,
          1,
          0,
          1,
          2,
          0,
          0,
          0,
          0,
          2,
          0,
          1,
          0,
          0,
          3,
          0,
          1,
          0,
          1,
          2,
          1,
          1,
          1,
          0,
          3,
          1,
          0,
          3,
          1,
          0,
          1,
          1,
          0,
          4,
          2,
          0,
          0,
          0,
          1,
          1,
          0,
          1,
          0,
          1,
          2,
          0,
          0,
          0,
          2,
          2,
          1,
          1,
          1,
          1,
          0,
          0,
          1,
          3,
          0,
          1,
          2,
          1,
          1,
          1,
          2,
          2,
          1,
          0,
          0,
          2,
          2,
          0,
          1,
          5,
          1,
          2,
          1,
          1,
          0,
          0,
          1,
          3,
          1,
          0,
          1,
          0,
          0,
          4,
          0,
          1,
          2,
          2,
          2,
          1,
          1,
          4,
          2,
          1,
          1,
          2,
          0,
          3,
          1,
          0,
          2,
          5,
          2,
          2,
          1,
          2,
          1,
          0,
          2,
          1,
          2,
          2,
          2,
          2,
          0,
          0,
          3,
          4,
          3,
          3,
          1,
          1,
          0,
          2,
          1,
          2,
          1,
          0,
          0,
          2,
          1,
          2,
          3,
          3,
          3,
          4,
          4,
          0,
          2,
          1,
          1,
          2,
          4,
          0,
          2,
          2,
          2,
          3,
          3,
          2,
          4,
          3,
          3,
          1,
          2,
          3,
          2,
          5,
          1,
          3,
          2,
          2,
          0,
          2,
          2,
          0,
          1,
          0,
          0,
          0,
          0,
          0,
          0,
          0,
          0,
          0,
          0,
          0,
          0,
          0,
          3,
          0,
          1,
          0,
          0,
          0,
          1,
          1,
          1,
          0,
          1,
          0,
          1,
          0,
          0,
          0,
          0,
          0,
          0,
          0,
          1,
          1,
          0,
          0,
          1,
          1,
          1,
          1,
          1,
          1,
          0,
          1,
          0,
          0,
          0,
          0,
          0,
          0,
          0,
          1,
          0,
          1,
          0,
          0,
          1,
          0,
          0,
          0,
          0,
          0,
          1,
          0,
          1,
          1,
          0,
          0,
          0,
          1,
          0,
          0,
          0,
          1,
          1,
          1,
          3,
          2,
          0
        ],
        "in_transit": [
          30,
          48,
          50,
          60,
          50,
          58,
          59,
          54,
          44,
          49,
          43,
          47,
          48,
          42,
          45,
          45,
          50,
          57,
          55,
          45,
          40,
          49,
          52,
          55,
          58,
          62,
          64,
          69,
          56,
          49,
          53,
          54,
          59,
          52,
          50,
          59,
          51,
          56,
          52,
          52,
          48,
          50,
          50,
          49,
          60,
          55,
          61,
          64,
          65,
          55,
          48,
          48,
          52,
          52,
          63,
          57,
          44,
          51,
          49,
          43,
          54,
          58,
          55,
          45,
          48,
          41,
          44,
          42,
          37,
          44,
          59,
          56,
          62,
          54,
          39,
          32,
          39,
          48,
          54,
          50,
          57,
          69,
          71,
          78,
          84,
          79,
          77,
          69,
          82,
          83,
          72,
          72,
          89,
          80,
          76,
          74,
          67,
          59,
          83,
          78,
          75,
          82,
          81,
          80,
          69,
          76,
          65,
          70,
          62,
          72,
          69,
          65,
          67,
          65,
          59,
          60,
          67,
          61,
          69,
          66,
          61,
          61,
          68,
          65,
          76,
          67,
          81,
          80,
          87,
          67,
          82,
          83,
          97,
          90,
          85,
          83,
          77,
          83,
          74,
          89,
          79,
          83,
          82,
          78,
          67,
          86,
          88,
          86,
          79,
          82,
          74,
          76,
          88,
          84,
          82,
          80,
          77,
          87,
          83,
          82,
          66,
          56,
          75,
          69,
          70,
          65,
          53,
          53,
          47,
          48,
          47,
          49,
          51,
          43,
          41,
          38,
          46,
          44,
          45,
          51,
          44,
          57,
          47,
          44,
          53,
          41,
          39,
          35,
          50,
          55,
          65,
          65,
          55,
          48,
          41,
          41,
          40,
          50,
          49,
          51,
          54,
          55,
          52,
          48,
          48,
          43,
          39,
          36,
          38,
          41,
          45,
          50,
          47,
          51,
          51,
          48,
          45,
          40,
          47,
          54,
          51,
          52,
          53,
          48,
          53,
          67,
          61,
          54,
          53,
          44,
          42,
          53,
          46,
          48,
          62,
          69,
          62,
          50,
          50,
          54,
          44,
          40,
          38,
          38,
          40,
          33,
          40,
          36,
          39,
          48,
          33,
          32,
          25,
          29,
          34,
          32,
          23,
          24,
          19,
          26,
          28,
          25,
          24,
          27,
          30,
          28,
          46,
          35,
          30,
          32,
          38,
          30,
          25,
          34,
          30,
          30,
          37,
          31,
          30,
          30,
          30,
          32,
          25,
          29,
          31,
          28,
          32,
          31,
          27,
          46,
          40,
          34,
          28,
          23,
          27,
          22,
          32,
          31,
          33,
          33,
          34,
          28,
          24,
          25,
          31,
          34,
          26,
          40,
          29,
          25,
          18,
          24,
          23,
          16,
          29,
          38,
          39,
          37,
          38,
          34,
          0
        ],
        "injected": [
          30,
          20,
          25,
          24,
          21,
          28,
          25,
          19,
          17,
          17,
          21,
          21,
          23,
          16,
          20,
          15,
          26,
          23,
          21,
          10,
          17,
          23,
          18,
          24,
          24,
          31,
          27,
          26,
          19,
          19,
          23,
          21,
          24,
          21,
          23,
          22,
          19,
          24,
          21,
          17,
          22,
          26,
          14,
          20,
          29,
          24,
          25,
          21,
          20,
          27,
          17,
          20,
          29,
          22,
          30,
          17,
          14,
          27,
          17,
          18,
          30,
          29,
          15,
          21,
          19,
          17,
          18,
          16,
          16,
          26,
          27,
          22,
          25,
          20,
          14,
          7,
          21,
          28,
          21,
          17,
          37,
          33,
          32,
          32,
          34,
          22,
          29,
          29,
          33,
          30,
          19,
          25,
          42,
          22,
          29,
          23,
          24,
          25,
          38,
          22,
          29,
          40,
          32,
          34,
          26,
          29,
          15,
          31,
          28,
          32,
          17,
          29,
          29,
          26,
          23,
          26,
          23,
          28,
          26,
          29,
          20,
          26,
          30,
          22,
          32,
          24,
          35,
          42,
          30,
          24,
          41,
          32,
          50,
          36,
          22,
          29,
          32,
          40,
          21,
          34,
          33,
          30,
          31,
          22,
          18,
          28,
          36,
          20,
          26,
          21,
          21,
          22,
          34,
          31,
          28,
          31,
          27,
          38,
          30,
          35,
          13,
          11,
          26,
          27,
          15,
          17,
          16,
          24,
          17,
          24,
          17,
          24,
          20,
          21,
          15,
          17,
          24,
          20,
          23,
          19,
          16,
          29,
          16,
          19,
          25,
          18,
          16,
          18,
          27,
          26,
          31,
          24,
          20,
          12,
          20,
          19,
          24,
          22,
          19,
          25,
          25,
          16,
          23,
          15,
          23,
          11,
          18,
          12,
          22,
          17,
          29,
          22,
          20,
          23,
          22,
          19,
          22,
          14,
          21,
          27,
          23,
          30,
          18,
          20,
          31,
          34,
          21,
          21,
          23,
          18,
          21,
          28,
          17,
          22,
          33,
          29,
          18,
          18,
          25,
          25,
          21,
          34,
          20,
          36,
          21,
          23,
          26,
          20,
          26,
          31,
          20,
          15,
          15,
          28,
          27,
          15,
          18,
          21,
          18,
          20,
          21,
          18,
          23,
          18,
          22,
          23,
          26,
          16,
          23,
          22,
          22,
          14,
          23,
          24,
          21,
          18,
          24,
          16,
          22,
          22,
          19,
          18,
          15,
          24,
          20,
          22,
          18,
          17,
          28,
          36,
          24,
          17,
          14,
          18,
          14,
          14,
          23,
          15,
          24,
          18,
          20,
          19,
          12,
          20,
          20,
          25,
          19,
          24,
          16,
          11,
          11,
          22,
          12,
          14,
          31,
          25,
          24,
          16,
          27,
          22,
          0
        ],
        "injected_unique": [
          24,
          16,
          20,
          21,
          19,
          23,
          23,
          15,
          15,
          15,
          19,
          19,
          18,
          14,
          18,
          13,
          22,
          21,
          18,
          9,
          14,
          22,
          13,
          21,
          22,
          28,
          22,
          19,
          17,
          17,
          19,
          18,
          18,
          18,
          20,
          19,
          15,
          20,
          19,
          16,
          19,
          19,
          11,
          16,
          27,
          23,
          20,
          18,
          17,
          21,
          16,
          18,
          24,
          17,
          24,
          14,
          11,
          23,
          13,
          15,
          26,
          25,
          14,
          19,
          18,
          15,
          15,
          13,
          12,
          23,
          24,
          18,
          21,
          17,
          13,
          7,
          18,
          23,
          17,
          15,
          30,
          28,
          28,
          25,
          29,
          22,
          24,
          27,
          28,
          29,
          16,
          21,
          33,
          20,
          25,
          21,
          19,
          20,
          31,
          19,
          23,
          30,
          28,
          30,
          25,
          26,
          14,
          27,
          25,
          24,
          15,
          29,
          24,
          22,
          19,
          25,
          22,
          22,
          22,
          25,
          16,
          23,
          24,
          19,
          26,
          22,
          27,
          32,
          25,
          23,
          34,
          25,
          41,
          29,
          18,
          25,
          27,
          34,
          17,
          30,
          27,
          26,
          28,
          19,
          17,
          24,
          31,
          19,
          23,
          18,
          17,
          21,
          27,
          24,
          24,
          27,
          22,
          33,
          24,
          30,
          13,
          9,
          22,
          21,
          13,
          16,
          13,
          22,
          16,
          19,
          13,
          21,
          18,
          18,
          11,
          14,
          22,
          18,
          21,
          16,
          13,
          25,
          16,
          15,
          21,
          16,
          15,
          13,
          20,
          22,
          22,
          19,
          17,
          12,
          18,
          15,
          20,
          20,
          18,
          20,
          22,
          12,
          19,
          14,
          19,
          10,
          13,
          9,
          18,
          13,
          24,
          19,
          17,
          21,
          19,
          19,
          20,
          13,
          18,
          23,
          20,
          24,
          15,
          15,
          25,
          22,
          17,
          19,
          19,
          16,
          18,
          24,
          13,
          21,
          26,
          22,
          15,
          17,
          19,
          20,
          18,
          30,
          19,
          27,
          17,
          22,
          23,
          16,
          19,
          26,
          16,
          14,
          12,
          22,
          23,
          13,
          16,
          17,
          14,
          18,
          18,
          16,
          20,
          18,
          19,
          18,
          21,
          15,
          19,
          18,
          18,
          12,
          16,
          19,
          16,
          15,
          19,
          15,
          18,
          19,
          17,
          16,
          14,
          20,
          18,
          20,
          16,
          17,
          22,
          28,
          19,
          15,
          13,
          15,
          12,
          13,
          18,
          14,
          20,
          15,
          15,
          15,
          10,
          17,
          18,
          22,
          18,
          18,
          13,
          10,
          11,
          18,
          11,
          14,
          25,
          21,
          21,
          16,
          23,
          19,
          0
        ]
      },
      "totals": {
        "avg_latency": 2.8141133343516116,
        "delivered": 6547,
        "delivered_unique": 5603,
        "delivery_ratio": 0.8868870224871308,
        "drop_ratio": 0.04416147385532376,
        "dropped": 326,
        "duplicate_deliveries": 944,
        "duplicate_delivery_ratio": 0.1684811708013564,
        "injected": 7382,
        "injected_unique": 6258,
        "p95_latency": 5.0,
        "stale_packet_deliveries": 657,
        "stale_unique_deliveries": 524,
        "stale_unique_ratio": 0.09352132786007496,
        "timely_unique_delivery_ratio": 0.8116011505273251,
        "unique_delivery_ratio": 0.8953339725151805
      },
      "traffic_mode": "poisson"
    },
    "min_cost_lp": {
      "coordination_kpis": {
        "alert_duplicate_rate": 0.9149507609668756,
        "handoff_success_rate": 0.9640718562874252,
        "handoff_timely_success_rate": 0.9640718562874252
      },
      "per_commodity": {
        "alert_cam1": {
          "avg_latency": 2.4781746031746033,
          "avg_unique_latency": 2.431297709923664,
          "copies": 2,
          "delivered": 504,
          "delivered_unique": 262,
          "delivery_ratio": 0.9618320610687023,
          "dropped": 20,
          "duplicate_deliveries": 242,
          "duplicate_per_unique": 0.9236641221374046,
          "injected": 524,
          "injected_unique": 262,
          "kind": "alert",
          "p95_latency": 5.0,
          "p95_unique_latency": 5.0,
          "stale_packet_deliveries": 55,
          "stale_unique_deliveries": 26,
          "stale_unique_ratio": 0.09923664122137404,
          "timely_unique_deliveries": 236,
          "timely_unique_ratio": 0.9007633587786259,
          "ttl_steps": 3,
          "unique_delivery_ratio": 1.0
        },
        "alert_cam2": {
          "avg_latency": 2.522504892367906,
          "avg_unique_latency": 2.4797047970479706,
          "copies": 2,
          "delivered": 511,
          "delivered_unique": 271,
          "delivery_ratio": 0.9257246376811594,
          "dropped": 37,
          "duplicate_deliveries": 240,
          "duplicate_per_unique": 0.8856088560885609,
          "injected": 552,
          "injected_unique": 276,
          "kind": "alert",
          "p95_latency": 5.0,
          "p95_unique_latency": 4.5,
          "stale_packet_deliveries": 57,
          "stale_unique_deliveries": 27,
          "stale_unique_ratio": 0.0996309963099631,
          "timely_unique_deliveries": 244,
          "timely_unique_ratio": 0.8840579710144928,
          "ttl_steps": 3,
          "unique_delivery_ratio": 0.9818840579710145
        },
        "alert_cam3": {
          "avg_latency": 2.3599290780141846,
          "avg_unique_latency": 2.335616438356164,
          "copies": 2,
          "delivered": 564,
          "delivered_unique": 292,
          "delivery_ratio": 0.9657534246575342,
          "dropped": 20,
          "duplicate_deliveries": 272,
          "duplicate_per_unique": 0.9315068493150684,
          "injected": 584,
          "injected_unique": 292,
          "kind": "alert",
          "p95_latency": 4.0,
          "p95_unique_latency": 4.0,
          "stale_packet_deliveries": 50,
          "stale_unique_deliveries": 23,
          "stale_unique_ratio": 0.07876712328767123,
          "timely_unique_deliveries": 269,
          "timely_unique_ratio": 0.9212328767123288,
          "ttl_steps": 3,
          "unique_delivery_ratio": 1.0
        },
        "alert_cam4": {
          "avg_latency": 2.4482142857142857,
          "avg_unique_latency": 2.410958904109589,
          "copies": 2,
          "delivered": 560,
          "delivered_unique": 292,
          "delivery_ratio": 0.9523809523809523,
          "dropped": 23,
          "duplicate_deliveries": 268,
          "duplicate_per_unique": 0.9178082191780822,
          "injected": 588,
          "injected_unique": 294,
          "kind": "alert",
          "p95_latency": 5.0,
          "p95_unique_latency": 5.0,
          "stale_packet_deliveries": 62,
          "stale_unique_deliveries": 28,
          "stale_unique_ratio": 0.0958904109589041,
          "timely_unique_deliveries": 264,
          "timely_unique_ratio": 0.8979591836734694,
          "ttl_steps": 3,
          "unique_delivery_ratio": 0.9931972789115646
        },
        "handoff_1_2": {
          "avg_latency": 1.0,
          "avg_unique_latency": 1.0,
          "copies": 1,
          "delivered": 202,
          "delivered_unique": 202,
          "delivery_ratio": 0.9758454106280193,
          "dropped": 5,
          "duplicate_deliveries": 0,
          "duplicate_per_unique": 0.0,
          "injected": 207,
          "injected_unique": 207,
          "kind": "handoff",
          "p95_latency": 1.0,
          "p95_unique_latency": 1.0,
          "stale_packet_deliveries": 0,
          "stale_unique_deliveries": 0,
          "stale_unique_ratio": 0.0,
          "timely_unique_deliveries": 202,
          "timely_unique_ratio": 0.9758454106280193,
          "ttl_steps": 4,
          "unique_delivery_ratio": 0.9758454106280193
        },
        "handoff_2_3": {
          "avg_latency": 1.0,
          "avg_unique_latency": 1.0,
          "copies": 1,
          "delivered": 215,
          "delivered_unique": 215,
          "delivery_ratio": 0.9347826086956522,
          "dropped": 15,
          "duplicate_deliveries": 0,
          "duplicate_per_unique": 0.0,
          "injected": 230,
          "injected_unique": 230,
          "kind": "handoff",
          "p95_latency": 1.0,
          "p95_unique_latency": 1.0,
          "stale_packet_deliveries": 0,
          "stale_unique_deliveries": 0,
          "stale_unique_ratio": 0.0,
          "timely_unique_deliveries": 215,
          "timely_unique_ratio": 0.9347826086956522,
          "ttl_steps": 4,
          "unique_delivery_ratio": 0.9347826086956522
        },
        "handoff_3_4": {
          "avg_latency": 1.0088105726872247,
          "avg_unique_latency": 1.0088105726872247,
          "copies": 1,
          "delivered": 227,
          "delivered_unique": 227,
          "delivery_ratio": 0.9826839826839827,
          "dropped": 4,
          "duplicate_deliveries": 0,
          "duplicate_per_unique": 0.0,
          "injected": 231,
          "injected_unique": 231,
          "kind": "handoff",
          "p95_latency": 1.0,
          "p95_unique_latency": 1.0,
          "stale_packet_deliveries": 0,
          "stale_unique_deliveries": 0,
          "stale_unique_ratio": 0.0,
          "timely_unique_deliveries": 227,
          "timely_unique_ratio": 0.9826839826839827,
          "ttl_steps": 4,
          "unique_delivery_ratio": 0.9826839826839827
        },
        "heartbeat_1": {
          "avg_latency": 2.3563218390804597,
          "avg_unique_latency": 2.3563218390804597,
          "copies": 1,
          "delivered": 174,
          "delivered_unique": 174,
          "delivery_ratio": 0.9508196721311475,
          "dropped": 9,
          "duplicate_deliveries": 0,
          "duplicate_per_unique": 0.0,
          "injected": 183,
          "injected_unique": 183,
          "kind": "heartbeat",
          "p95_latency": 4.0,
          "p95_unique_latency": 4.0,
          "stale_packet_deliveries": 28,
          "stale_unique_deliveries": 28,
          "stale_unique_ratio": 0.16091954022988506,
          "timely_unique_deliveries": 146,
          "timely_unique_ratio": 0.7978142076502732,
          "ttl_steps": 2,
          "unique_delivery_ratio": 0.9508196721311475
        },
        "heartbeat_2": {
          "avg_latency": 2.6354679802955663,
          "avg_unique_latency": 2.6354679802955663,
          "copies": 1,
          "delivered": 203,
          "delivered_unique": 203,
          "delivery_ratio": 0.9441860465116279,
          "dropped": 12,
          "duplicate_deliveries": 0,
          "duplicate_per_unique": 0.0,
          "injected": 215,
          "injected_unique": 215,
          "kind": "heartbeat",
          "p95_latency": 6.0,
          "p95_unique_latency": 6.0,
          "stale_packet_deliveries": 45,
          "stale_unique_deliveries": 45,
          "stale_unique_ratio": 0.22167487684729065,
          "timely_unique_deliveries": 158,
          "timely_unique_ratio": 0.7348837209302326,
          "ttl_steps": 2,
          "unique_delivery_ratio": 0.9441860465116279
        },
        "heartbeat_3": {
          "avg_latency": 2.4216867469879517,
          "avg_unique_latency": 2.4216867469879517,
          "copies": 1,
          "delivered": 166,
          "delivered_unique": 166,
          "delivery_ratio": 0.9595375722543352,
          "dropped": 7,
          "duplicate_deliveries": 0,
          "duplicate_per_unique": 0.0,
          "injected": 173,
          "injected_unique": 173,
          "kind": "heartbeat",
          "p95_latency": 4.0,
          "p95_unique_latency": 4.0,
          "stale_packet_deliveries": 39,
          "stale_unique_deliveries": 39,
          "stale_unique_ratio": 0.23493975903614459,
          "timely_unique_deliveries": 127,
          "timely_unique_ratio": 0.7341040462427746,
          "ttl_steps": 2,
          "unique_delivery_ratio": 0.9595375722543352
        },
        "heartbeat_4": {
          "avg_latency": 2.287958115183246,
          "avg_unique_latency": 2.287958115183246,
          "copies": 1,
          "delivered": 191,
          "delivered_unique": 191,
          "delivery_ratio": 0.9646464646464646,
          "dropped": 6,
          "duplicate_deliveries": 0,
          "duplicate_per_unique": 0.0,
          "injected": 198,
          "injected_unique": 198,
          "kind": "heartbeat",
          "p95_latency": 4.0,
          "p95_unique_latency": 4.0,
          "stale_packet_deliveries": 33,
          "stale_unique_deliveries": 33,
          "stale_unique_ratio": 0.17277486910994763,
          "timely_unique_deliveries": 158,
          "timely_unique_ratio": 0.797979797979798,
          "ttl_steps": 2,
          "unique_delivery_ratio": 0.9646464646464646
        },
        "track_cam1": {
          "avg_latency": 2.273532668881506,
          "avg_unique_latency": 2.273532668881506,
          "copies": 1,
          "delivered": 903,
          "delivered_unique": 903,
          "delivery_ratio": 0.9709677419354839,
          "dropped": 26,
          "duplicate_deliveries": 0,
          "duplicate_per_unique": 0.0,
          "injected": 930,
          "injected_unique": 930,
          "kind": "track",
          "p95_latency": 4.0,
          "p95_unique_latency": 4.0,
          "stale_packet_deliveries": 3,
          "stale_unique_deliveries": 3,
          "stale_unique_ratio": 0.0033222591362126247,
          "timely_unique_deliveries": 900,
          "timely_unique_ratio": 0.967741935483871,
          "ttl_steps": 8,
          "unique_delivery_ratio": 0.9709677419354839
        },
        "track_cam2": {
          "avg_latency": 2.550228310502283,
          "avg_unique_latency": 2.550228310502283,
          "copies": 1,
          "delivered": 876,
          "delivered_unique": 876,
          "delivery_ratio": 0.9201680672268907,
          "dropped": 73,
          "duplicate_deliveries": 0,
          "duplicate_per_unique": 0.0,
          "injected": 952,
          "injected_unique": 952,
          "kind": "track",
          "p95_latency": 6.0,
          "p95_unique_latency": 6.0,
          "stale_packet_deliveries": 4,
          "stale_unique_deliveries": 4,
          "stale_unique_ratio": 0.0045662100456621,
          "timely_unique_deliveries": 872,
          "timely_unique_ratio": 0.9159663865546218,
          "ttl_steps": 8,
          "unique_delivery_ratio": 0.9201680672268907
        },
        "track_cam3": {
          "avg_latency": 2.386946386946387,
          "avg_unique_latency": 2.386946386946387,
          "copies": 1,
          "delivered": 858,
          "delivered_unique": 858,
          "delivery_ratio": 0.958659217877095,
          "dropped": 35,
          "duplicate_deliveries": 0,
          "duplicate_per_unique": 0.0,
          "injected": 895,
          "injected_unique": 895,
          "kind": "track",
          "p95_latency": 4.0,
          "p95_unique_latency": 4.0,
          "stale_packet_deliveries": 0,
          "stale_unique_deliveries": 0,
          "stale_unique_ratio": 0.0,
          "timely_unique_deliveries": 858,
          "timely_unique_ratio": 0.958659217877095,
          "ttl_steps": 8,
          "unique_delivery_ratio": 0.958659217877095
        },
        "track_cam4": {
          "avg_latency": 2.382420091324201,
          "avg_unique_latency": 2.382420091324201,
          "copies": 1,
          "delivered": 876,
          "delivered_unique": 876,
          "delivery_ratio": 0.9521739130434783,
          "dropped": 35,
          "duplicate_deliveries": 0,
          "duplicate_per_unique": 0.0,
          "injected": 920,
          "injected_unique": 920,
          "kind": "track",
          "p95_latency": 4.0,
          "p95_unique_latency": 4.0,
          "stale_packet_deliveries": 8,
          "stale_unique_deliveries": 8,
          "stale_unique_ratio": 0.0091324200913242,
          "timely_unique_deliveries": 868,
          "timely_unique_ratio": 0.9434782608695652,
          "ttl_steps": 8,
          "unique_delivery_ratio": 0.9521739130434783
        }
      },
      "policy": "min_cost_lp",
      "steps": 320,
      "timeseries": {
        "backlog": [
          0,
          0,
          0,
          0,
          0,
          0,
          0,
          0,
          0,
          0,
          0,
          0,
          0,
          0,
          0,
          0,
          0,
          0,
          0,
          0,
          0,
          0,
          0,
          0,
          0,
          0,
          0,
          0,
          0,
          0,
          0,
          0,
          0,
          0,
          0,
          0,
          0,
          0,
          0,
          0,
          0,
          0,
          0,
          0,
          0,
          0,
          0,
          0,
          0,
          0,
          0,
          0,
          0,
          0,
          0,
          0,
          0,
          0,
          0,
          0,
          2,
          0,
          0,
          0,
          0,
          0,
          0,
          0,
          0,
          0,
          0,
          0,
          0,
          0,
          0,
          0,
          0,
          0,
          0,
          0,
          0,
          2,
          2,
          8,
          10,
          10,
          9,
          5,
          7,
          18,
          5,
          7,
          4,
          15,
          1,
          6,
          2,
          5,
          0,
          3,
          1,
          7,
          7,
          7,
          6,
          14,
          5,
          2,
          4,
          3,
          7,
          0,
          1,
          3,
          0,
          1,
          0,
          4,
          2,
          2,
          3,
          0,
          0,
          0,
          0,
          1,
          0,
          5,
          7,
          10,
          6,
          12,
          22,
          32,
          34,
          26,
          31,
          35,
          44,
          34,
          43,
          44,
          50,
          39,
          39,
          24,
          28,
          38,
          32,
          24,
          18,
          14,
          12,
          23,
          21,
          24,
          19,
          18,
          27,
          26,
          29,
          10,
          4,
          7,
          2,
          0,
          0,
          0,
          0,
          0,
          0,
          0,
          0,
          0,
          0,
          0,
          0,
          0,
          0,
          0,
          0,
          0,
          0,
          0,
          0,
          0,
          0,
          0,
          0,
          0,
          0,
          2,
          0,
          0,
          0,
          0,
          0,
          0,
          0,
          0,
          0,
          0,
          0,
          0,
          0,
          0,
          0,
          0,
          0,
          0,
          0,
          0,
          0,
          0,
          0,
          0,
          0,
          0,
          0,
          0,
          0,
          0,
          0,
          0,
          0,
          0,
          0,
          0,
          0,
          0,
          0,
          0,
          0,
          0,
          0,
          0,
          2,
          0,
          0,
          0,
          0,
          0,
          0,
          0,
          0,
          0,
          0,
          0,
          0,
          0,
          0,
          0,
          0,
          0,
          0,
          0,
          0,
          0,
          0,
          0,
          0,
          0,
          0,
          0,
          0,
          0,
          0,
          0,
          0,
          0,
          0,
          0,
          0,
          0,
          0,
          0,
          0,
          0,
          0,
          0,
          0,
          0,
          0,
          0,
          0,
          0,
          0,
          0,
          0,
          0,
          1,
          0,
          0,
          0,
          0,
          0,
          0,
          0,
          0,
          0,
          0,
          0,
          0,
          0,
          0,
          0,
          0,
          0,
          0,
          0,
          0,
          0,
          0,
          0,
          0,
          0,
          0,
          0,
          0,
          1,
          25
        ],
        "context": [
          "normal",
          "normal",
          "normal",
          "normal",
          "normal",
          "normal",
          "normal",
          "normal",
          "normal",
          "normal",
          "normal",
          "normal",
          "normal",
          "normal",
          "normal",
          "normal",
          "normal",
          "normal",
          "normal",
          "normal",
          "normal",
          "normal",
          "normal",
          "normal",
          "normal",
          "normal",
          "normal",
          "normal",
          "normal",
          "normal",
          "normal",
          "normal",
          "normal",
          "normal",
          "normal",
          "normal",
          "normal",
          "normal",
          "normal",
          "normal",
          "normal",
          "normal",
          "normal",
          "normal",
          "normal",
          "normal",
          "normal",
          "normal",
          "normal",
          "normal",
          "normal",
          "normal",
          "normal",
          "normal",
          "normal",
          "normal",
          "normal",
          "normal",
          "normal",
          "normal",
          "normal",
          "normal",
          "normal",
          "normal",
          "normal",
          "normal",
          "normal",
          "normal",
          "normal",
          "normal",
          "normal",
          "normal",
          "normal",
          "normal",
          "normal",
          "normal",
          "normal",
          "normal",
          "normal",
          "normal",
          "crowded",
          "crowded",
          "crowded",
          "crowded",
          "crowded",
          "crowded",
          "crowded",
          "crowded",
          "crowded",
          "crowded",
          "crowded",
          "crowded",
          "crowded",
          "crowded",
          "crowded",
          "crowded",
          "crowded",
          "crowded",
          "crowded",
          "crowded",
          "crowded",
          "crowded",
          "crowded",
          "crowded",
          "crowded",
          "crowded",
          "crowded",
          "crowded",
          "crowded",
          "crowded",
          "crowded",
          "crowded",
          "crowded",
          "crowded",
          "crowded",
          "crowded",
          "crowded",
          "crowded",
          "crowded",
          "crowded",
          "crowded",
          "crowded",
          "crowded",
          "crowded",
          "crowded",
          "crowded",
          "crowded",
          "crowded",
          "crowded",
          "crowded",
          "crowded",
          "crowded",
          "crowded",
          "crowded",
          "crowded",
          "crowded",
          "crowded",
          "crowded",
          "crowded",
          "crowded",
          "crowded",
          "crowded",
          "crowded",
          "crowded",
          "crowded",
          "crowded",
          "crowded",
          "crowded",
          "crowded",
          "crowded",
          "crowded",
          "crowded",
          "crowded",
          "crowded",
          "crowded",
          "crowded",
          "crowded",
          "crowded",
          "crowded",
          "crowded",
          "uplink_loss",
          "uplink_loss",
          "uplink_loss",
          "uplink_loss",
          "uplink_loss",
          "uplink_loss",
          "uplink_loss",
          "uplink_loss",
          "uplink_loss",
          "uplink_loss",
          "uplink_loss",
          "uplink_loss",
          "uplink_loss",
          "uplink_loss",
          "uplink_loss",
          "uplink_loss",
          "uplink_loss",
          "uplink_loss",
          "uplink_loss",
          "uplink_loss",
          "uplink_loss",
          "uplink_loss",
          "uplink_loss",
          "uplink_loss",
          "uplink_loss",
          "uplink_loss",
          "uplink_loss",
          "uplink_loss",
          "uplink_loss",
          "uplink_loss",
          "uplink_loss",
          "uplink_loss",
          "uplink_loss",
          "uplink_loss",
          "uplink_loss",
          "uplink_loss",
          "uplink_loss",
          "uplink_loss",
          "uplink_loss",
          "uplink_loss",
          "uplink_loss",
          "uplink_loss",
          "uplink_loss",
          "uplink_loss",
          "uplink_loss",
          "uplink_loss",
          "uplink_loss",
          "uplink_loss",
          "uplink_loss",
          "uplink_loss",
          "uplink_loss",
          "uplink_loss",
          "uplink_loss",
          "uplink_loss",
          "uplink_loss",
          "uplink_loss",
          "uplink_loss",
          "uplink_loss",
          "uplink_loss",
          "uplink_loss",
          "uplink_loss",
          "uplink_loss",
          "uplink_loss",
          "uplink_loss",
          "uplink_loss",
          "uplink_loss",
          "uplink_loss",
          "uplink_loss",
          "uplink_loss",
          "uplink_loss",
          "uplink_loss",
          "uplink_loss",
          "uplink_loss",
          "uplink_loss",
          "uplink_loss",
          "uplink_loss",
          "uplink_loss",
          "uplink_loss",
          "uplink_loss",
          "uplink_loss",
          "cam2_failure",
          "cam2_failure",
          "cam2_failure",
          "cam2_failure",
          "cam2_failure",
          "cam2_failure",
          "cam2_failure",
          "cam2_failure",
          "cam2_failure",
          "cam2_failure",
          "cam2_failure",
          "cam2_failure",
          "cam2_failure",
          "cam2_failure",
          "cam2_failure",
          "cam2_failure",
          "cam2_failure",
          "cam2_failure",
          "cam2_failure",
          "cam2_failure",
          "cam2_failure",
          "cam2_failure",
          "cam2_failure",
          "cam2_failure",
          "cam2_failure",
          "cam2_failure",
          "cam2_failure",
          "cam2_failure",
          "cam2_failure",
          "cam2_failure",
          "cam2_failure",
          "cam2_failure",
          "cam2_failure",
          "cam2_failure",
          "cam2_failure",
          "cam2_failure",
          "cam2_failure",
          "cam2_failure",
          "cam2_failure",
          "cam2_failure",
          "cam2_failure",
          "cam2_failure",
          "cam2_failure",
          "cam2_failure",
          "cam2_failure",
          "cam2_failure",
          "cam2_failure",
          "cam2_failure",
          "cam2_failure",
          "cam2_failure",
          "cam2_failure",
          "cam2_failure",
          "cam2_failure",
          "cam2_failure",
          "cam2_failure",
          "cam2_failure",
          "cam2_failure",
          "cam2_failure",
          "cam2_failure",
          "cam2_failure",
          "cam2_failure",
          "cam2_failure",
          "cam2_failure",
          "cam2_failure",
          "cam2_failure",
          "cam2_failure",
          "cam2_failure",
          "cam2_failure",
          "cam2_failure",
          "cam2_failure",
          "cam2_failure",
          "cam2_failure",
          "cam2_failure",
          "cam2_failure",
          "cam2_failure",
          "cam2_failure",
          "cam2_failure",
          "cam2_failure",
          "cam2_failure",
          "cam2_failure",
          "drain"
        ],
        "delivered": [
          0,
          2,
          24,
          25,
          24,
          23,
          22,
          24,
          27,
          22,
          16,
          18,
          18,
          20,
          21,
          17,
          19,
          16,
          25,
          18,
          24,
          10,
          18,
          22,
          18,
          24,
          24,
          28,
          28,
          29,
          15,
          21,
          21,
          22,
          24,
          20,
          25,
          19,
          18,
          26,
          19,
          17,
          19,
          22,
          20,
          17,
          25,
          24,
          26,
          21,
          22,
          26,
          14,
          22,
          28,
          21,
          26,
          19,
          16,
          24,
          15,
          19,
          25,
          30,
          19,
          18,
          17,
          20,
          15,
          15,
          18,
          21,
          28,
          22,
          23,
          22,
          14,
          7,
          21,
          23,
          22,
          16,
          28,
          29,
          26,
          26,
          28,
          26,
          32,
          26,
          29,
          27,
          28,
          29,
          30,
          28,
          29,
          28,
          25,
          29,
          29,
          28,
          29,
          27,
          28,
          29,
          32,
          29,
          26,
          27,
          26,
          28,
          22,
          26,
          28,
          25,
          27,
          26,
          20,
          26,
          28,
          27,
          23,
          27,
          28,
          27,
          27,
          27,
          27,
          28,
          26,
          28,
          28,
          28,
          28,
          25,
          26,
          30,
          27,
          28,
          28,
          30,
          31,
          26,
          30,
          26,
          25,
          26,
          28,
          28,
          27,
          27,
          25,
          26,
          28,
          27,
          26,
          30,
          28,
          29,
          29,
          29,
          26,
          28,
          30,
          27,
          16,
          23,
          17,
          23,
          15,
          24,
          13,
          24,
          20,
          19,
          13,
          20,
          20,
          21,
          20,
          19,
          18,
          23,
          13,
          20,
          20,
          18,
          12,
          18,
          25,
          21,
          24,
          30,
          19,
          11,
          23,
          18,
          21,
          21,
          17,
          21,
          22,
          18,
          21,
          13,
          21,
          11,
          18,
          11,
          20,
          19,
          27,
          17,
          20,
          19,
          24,
          16,
          19,
          14,
          24,
          22,
          23,
          24,
          20,
          18,
          27,
          26,
          26,
          22,
          19,
          19,
          20,
          24,
          19,
          18,
          25,
          27,
          22,
          17,
          22,
          26,
          21,
          28,
          22,
          30,
          28,
          19,
          25,
          16,
          27,
          26,
          18,
          13,
          17,
          21,
          29,
          12,
          19,
          19,
          15,
          19,
          19,
          17,
          19,
          17,
          19,
          24,
          20,
          17,
          22,
          21,
          22,
          13,
          24,
          18,
          17,
          20,
          21,
          16,
          23,
          20,
          19,
          18,
          14,
          24,
          18,
          24,
          12,
          19,
          23,
          27,
          29,
          16,
          14,
          17,
          16,
          12,
          22,
          16,
          23,
          18,
          22,
          17,
          10,
          18,
          20,
          23,
          22,
          20,
          14,
          12,
          9,
          22,
          10,
          12,
          22,
          24,
          22,
          17,
          21
        ],
        "dropped": [
          0,
          0,
          1,
          0,
          1,
          1,
          0,
          0,
          0,
          0,
          2,
          0,
          0,
          1,
          0,
          0,
          1,
          0,
          0,
          1,
          0,
          0,
          0,
          0,
          2,
          0,
          0,
          0,
          0,
          0,
          0,
          1,
          1,
          0,
          0,
          0,
          1,
          0,
          0,
          1,
          0,
          2,
          0,
          2,
          1,
          0,
          2,
          0,
          0,
          0,
          0,
          2,
          0,
          1,
          0,
          0,
          0,
          1,
          2,
          0,
          0,
          0,
          0,
          2,
          2,
          0,
          0,
          1,
          0,
          2,
          0,
          0,
          0,
          0,
          0,
          0,
          1,
          0,
          2,
          1,
          0,
          0,
          0,
          0,
          1,
          0,
          1,
          0,
          2,
          2,
          0,
          0,
          2,
          0,
          1,
          0,
          0,
          2,
          0,
          0,
          1,
          1,
          2,
          2,
          0,
          0,
          0,
          0,
          2,
          0,
          1,
          0,
          3,
          0,
          0,
          0,
          0,
          1,
          0,
          0,
          3,
          1,
          1,
          0,
          0,
          0,
          0,
          2,
          0,
          1,
          0,
          1,
          4,
          0,
          3,
          2,
          1,
          1,
          1,
          0,
          2,
          0,
          3,
          0,
          1,
          2,
          2,
          0,
          1,
          2,
          1,
          1,
          0,
          1,
          1,
          4,
          0,
          0,
          3,
          2,
          1,
          3,
          2,
          2,
          3,
          0,
          1,
          1,
          0,
          1,
          1,
          2,
          1,
          1,
          2,
          1,
          0,
          1,
          1,
          1,
          1,
          3,
          1,
          3,
          1,
          3,
          3,
          1,
          1,
          1,
          2,
          2,
          2,
          1,
          0,
          1,
          1,
          1,
          2,
          3,
          2,
          1,
          1,
          1,
          1,
          1,
          1,
          0,
          2,
          0,
          1,
          2,
          3,
          3,
          0,
          3,
          0,
          1,
          2,
          2,
          0,
          2,
          1,
          1,
          2,
          4,
          2,
          1,
          0,
          1,
          2,
          2,
          1,
          1,
          3,
          2,
          0,
          1,
          3,
          0,
          1,
          1,
          2,
          1,
          0,
          2,
          3,
          1,
          3,
          1,
          3,
          2,
          1,
          5,
          1,
          0,
          0,
          1,
          1,
          4,
          1,
          2,
          1,
          3,
          1,
          1,
          1,
          0,
          3,
          2,
          2,
          0,
          0,
          3,
          3,
          2,
          0,
          1,
          2,
          0,
          0,
          0,
          0,
          2,
          0,
          2,
          1,
          1,
          2,
          1,
          3,
          1,
          2,
          0,
          0,
          0,
          0,
          1,
          0,
          0,
          0,
          1,
          0,
          2,
          1,
          1,
          2,
          2,
          0,
          1,
          1,
          0,
          2,
          2,
          3,
          2,
          2,
          0,
          1,
          4,
          0
        ],
        "in_transit": [
          30,
          48,
          48,
          47,
          43,
          47,
          50,
          45,
          35,
          30,
          33,
          36,
          41,
          36,
          35,
          33,
          39,
          46,
          42,
          33,
          26,
          39,
          39,
          41,
          45,
          52,
          55,
          53,
          44,
          34,
          42,
          41,
          43,
          42,
          41,
          43,
          36,
          41,
          44,
          34,
          37,
          44,
          39,
          35,
          43,
          50,
          48,
          45,
          39,
          45,
          40,
          32,
          47,
          46,
          48,
          44,
          32,
          39,
          38,
          32,
          45,
          57,
          47,
          36,
          34,
          33,
          34,
          29,
          30,
          39,
          48,
          49,
          46,
          44,
          35,
          20,
          26,
          47,
          45,
          38,
          53,
          68,
          72,
          69,
          74,
          70,
          71,
          78,
          75,
          66,
          69,
          65,
          80,
          62,
          74,
          64,
          63,
          55,
          73,
          63,
          64,
          69,
          70,
          75,
          74,
          66,
          58,
          63,
          61,
          67,
          53,
          61,
          64,
          62,
          60,
          60,
          57,
          54,
          62,
          65,
          53,
          54,
          60,
          55,
          59,
          55,
          64,
          72,
          73,
          65,
          84,
          81,
          89,
          87,
          76,
          86,
          86,
          91,
          75,
          91,
          85,
          84,
          75,
          82,
          69,
          84,
          89,
          73,
          76,
          75,
          74,
          72,
          83,
          76,
          77,
          74,
          80,
          89,
          79,
          84,
          64,
          62,
          66,
          60,
          47,
          39,
          38,
          38,
          38,
          38,
          39,
          37,
          43,
          39,
          32,
          29,
          40,
          39,
          41,
          38,
          33,
          40,
          37,
          30,
          41,
          36,
          29,
          28,
          42,
          49,
          53,
          52,
          48,
          29,
          30,
          37,
          37,
          40,
          36,
          37,
          43,
          37,
          37,
          33,
          34,
          31,
          27,
          28,
          30,
          36,
          44,
          45,
          35,
          38,
          40,
          37,
          35,
          32,
          32,
          43,
          42,
          48,
          42,
          37,
          46,
          58,
          50,
          44,
          41,
          36,
          36,
          43,
          39,
          36,
          47,
          56,
          47,
          39,
          39,
          47,
          45,
          52,
          49,
          56,
          55,
          46,
          41,
          41,
          39,
          53,
          43,
          30,
          26,
          36,
          45,
          39,
          28,
          36,
          34,
          31,
          36,
          33,
          36,
          34,
          36,
          41,
          47,
          39,
          39,
          42,
          40,
          33,
          34,
          42,
          36,
          34,
          41,
          36,
          35,
          41,
          37,
          35,
          31,
          35,
          41,
          37,
          36,
          28,
          42,
          58,
          55,
          45,
          28,
          30,
          30,
          27,
          34,
          36,
          38,
          40,
          37,
          37,
          27,
          28,
          37,
          43,
          40,
          39,
          33,
          23,
          19,
          29,
          30,
          20,
          38,
          49,
          49,
          41,
          45,
          45,
          0
        ],
        "injected": [
          30,
          20,
          25,
          24,
          21,
          28,
          25,
          19,
          17,
          17,
          21,
          21,
          23,
          16,
          20,
          15,
          26,
          23,
          21,
          10,
          17,
          23,
          18,
          24,
          24,
          31,
          27,
          26,
          19,
          19,
          23,
          21,
          24,
          21,
          23,
          22,
          19,
          24,
          21,
          17,
          22,
          26,
          14,
          20,
          29,
          24,
          25,
          21,
          20,
          27,
          17,
          20,
          29,
          22,
          30,
          17,
          14,
          27,
          17,
          18,
          30,
          29,
          15,
          21,
          19,
          17,
          18,
          16,
          16,
          26,
          27,
          22,
          25,
          20,
          14,
          7,
          21,
          28,
          21,
          17,
          37,
          33,
          32,
          32,
          34,
          22,
          29,
          29,
          33,
          30,
          19,
          25,
          42,
          22,
          29,
          23,
          24,
          25,
          38,
          22,
          29,
          40,
          32,
          34,
          26,
          29,
          15,
          31,
          28,
          32,
          17,
          29,
          29,
          26,
          23,
          26,
          23,
          28,
          26,
          29,
          20,
          26,
          30,
          22,
          32,
          24,
          35,
          42,
          30,
          24,
          41,
          32,
          50,
          36,
          22,
          29,
          32,
          40,
          21,
          34,
          33,
          30,
          31,
          22,
          18,
          28,
          36,
          20,
          26,
          21,
          21,
          22,
          34,
          31,
          28,
          31,
          27,
          38,
          30,
          35,
          13,
          11,
          26,
          27,
          15,
          17,
          16,
          24,
          17,
          24,
          17,
          24,
          20,
          21,
          15,
          17,
          24,
          20,
          23,
          19,
          16,
          29,
          16,
          19,
          25,
          18,
          16,
          18,
          27,
          26,
          31,
          24,
          20,
          12,
          20,
          19,
          24,
          22,
          19,
          25,
          25,
          16,
          23,
          15,
          23,
          11,
          18,
          12,
          22,
          17,
          29,
          22,
          20,
          23,
          22,
          19,
          22,
          14,
          21,
          27,
          23,
          30,
          18,
          20,
          31,
          34,
          21,
          21,
          23,
          18,
          21,
          28,
          17,
          22,
          33,
          29,
          18,
          18,
          25,
          25,
          21,
          34,
          20,
          36,
          21,
          23,
          26,
          20,
          26,
          31,
          20,
          15,
          15,
          28,
          27,
          15,
          18,
          21,
          18,
          20,
          21,
          18,
          23,
          18,
          22,
          23,
          26,
          16,
          23,
          22,
          22,
          14,
          23,
          24,
          21,
          18,
          24,
          16,
          22,
          22,
          19,
          18,
          15,
          24,
          20,
          22,
          18,
          17,
          28,
          36,
          24,
          17,
          14,
          18,
          14,
          14,
          23,
          15,
          24,
          18,
          20,
          19,
          12,
          20,
          20,
          25,
          19,
          24,
          16,
          11,
          11,
          22,
          12,
          14,
          31,
          25,
          24,
          16,
          27,
          22,
          0
        ],
        "injected_unique": [
          24,
          16,
          20,
          21,
          19,
          23,
          23,
          15,
          15,
          15,
          19,
          19,
          18,
          14,
          18,
          13,
          22,
          21,
          18,
          9,
          14,
          22,
          13,
          21,
          22,
          28,
          22,
          19,
          17,
          17,
          19,
          18,
          18,
          18,
          20,
          19,
          15,
          20,
          19,
          16,
          19,
          19,
          11,
          16,
          27,
          23,
          20,
          18,
          17,
          21,
          16,
          18,
          24,
          17,
          24,
          14,
          11,
          23,
          13,
          15,
          26,
          25,
          14,
          19,
          18,
          15,
          15,
          13,
          12,
          23,
          24,
          18,
          21,
          17,
          13,
          7,
          18,
          23,
          17,
          15,
          30,
          28,
          28,
          25,
          29,
          22,
          24,
          27,
          28,
          29,
          16,
          21,
          33,
          20,
          25,
          21,
          19,
          20,
          31,
          19,
          23,
          30,
          28,
          30,
          25,
          26,
          14,
          27,
          25,
          24,
          15,
          29,
          24,
          22,
          19,
          25,
          22,
          22,
          22,
          25,
          16,
          23,
          24,
          19,
          26,
          22,
          27,
          32,
          25,
          23,
          34,
          25,
          41,
          29,
          18,
          25,
          27,
          34,
          17,
          30,
          27,
          26,
          28,
          19,
          17,
          24,
          31,
          19,
          23,
          18,
          17,
          21,
          27,
          24,
          24,
          27,
          22,
          33,
          24,
          30,
          13,
          9,
          22,
          21,
          13,
          16,
          13,
          22,
          16,
          19,
          13,
          21,
          18,
          18,
          11,
          14,
          22,
          18,
          21,
          16,
          13,
          25,
          16,
          15,
          21,
          16,
          15,
          13,
          20,
          22,
          22,
          19,
          17,
          12,
          18,
          15,
          20,
          20,
          18,
          20,
          22,
          12,
          19,
          14,
          19,
          10,
          13,
          9,
          18,
          13,
          24,
          19,
          17,
          21,
          19,
          19,
          20,
          13,
          18,
          23,
          20,
          24,
          15,
          15,
          25,
          22,
          17,
          19,
          19,
          16,
          18,
          24,
          13,
          21,
          26,
          22,
          15,
          17,
          19,
          20,
          18,
          30,
          19,
          27,
          17,
          22,
          23,
          16,
          19,
          26,
          16,
          14,
          12,
          22,
          23,
          13,
          16,
          17,
          14,
          18,
          18,
          16,
          20,
          18,
          19,
          18,
          21,
          15,
          19,
          18,
          18,
          12,
          16,
          19,
          16,
          15,
          19,
          15,
          18,
          19,
          17,
          16,
          14,
          20,
          18,
          20,
          16,
          17,
          22,
          28,
          19,
          15,
          13,
          15,
          12,
          13,
          18,
          14,
          20,
          15,
          15,
          15,
          10,
          17,
          18,
          22,
          18,
          18,
          13,
          10,
          11,
          18,
          11,
          14,
          25,
          21,
          21,
          16,
          23,
          19,
          0
        ]
      },
      "totals": {
        "avg_latency": 2.2890469416785204,
        "delivered": 7030,
        "delivered_unique": 6008,
        "delivery_ratio": 0.9523164454077486,
        "drop_ratio": 0.044296938499051745,
        "dropped": 327,
        "duplicate_deliveries": 1022,
        "duplicate_delivery_ratio": 0.17010652463382156,
        "injected": 7382,
        "injected_unique": 6258,
        "p95_latency": 4.0,
        "stale_packet_deliveries": 384,
        "stale_unique_deliveries": 264,
        "stale_unique_ratio": 0.043941411451398134,
        "timely_unique_delivery_ratio": 0.9178651326302333,
        "unique_delivery_ratio": 0.9600511345477788
      },
      "traffic_mode": "poisson"
    }
  },
  "seed": 9,
  "steps": 320,
  "traffic_mode": "poisson"
}